CHANGELOG
LICENSE
MANIFEST.in
README.rst
setup.py
apns_client.egg-info/PKG-INFO
apns_client.egg-info/SOURCES.txt
apns_client.egg-info/dependency_links.txt
apns_client.egg-info/requires.txt
apns_client.egg-info/top_level.txt
apnsclient/__init__.py
apnsclient/apns.py
apnsclient/certificate.py
apnsclient/transport.py
apnsclient/backends/__init__.py
apnsclient/backends/dummy.py
apnsclient/backends/stdio.py
test/test.py
test/test_stdio.py