Metadata-Version: 1.0
Name: apns-client
Version: 0.2
Summary: Python client for Apple Push Notification service (APNs)
Home-page: https://bitbucket.org/sardarnl/apns-client
Author: Sardar Yumatov
Author-email: ja.doma@gmail.com
License: Apache 2.0
Keywords: apns push notification apple messaging iOS
Platform: UNKNOWN
Classifier: Development Status :: 4 - Beta
Classifier: Intended Audience :: Developers
Classifier: License :: OSI Approved :: Apache Software License
Classifier: Programming Language :: Python
Classifier: Topic :: Software Development :: Libraries :: Python Modules
